bottleneck_transformer_pytorch/__init__.py
bottleneck_transformer_pytorch/bottleneck_transformer_pytorch.py
bottleneck_transformer_pytorch-0.1.4.dist-info/LICENSE
bottleneck_transformer_pytorch-0.1.4.dist-info/METADATA
bottleneck_transformer_pytorch-0.1.4.dist-info/WHEEL
bottleneck_transformer_pytorch-0.1.4.dist-info/top_level.txt
bottleneck_transformer_pytorch-0.1.4.dist-info/RECORD
